oswrapper/__init__.py
oswrapper-1.0.1.dist-info/METADATA
oswrapper-1.0.1.dist-info/WHEEL
oswrapper-1.0.1.dist-info/top_level.txt
oswrapper-1.0.1.dist-info/RECORD
