Metadata-Version: 2.1
Name: oswrapper
Version: 1.0.1
Summary: Wrapper for os package
Author: jaxonspears
Author-email: Jaxon Spears <jaxonspears@gmail.com>
License: MIT
Requires-Dist: requests
